tmg_biomechanics/__init__.py
tmg_biomechanics/constants.py
tmg_biomechanics/tmg_params.py
tmg_biomechanics-0.0.2.dist-info/LICENSE.md
tmg_biomechanics-0.0.2.dist-info/METADATA
tmg_biomechanics-0.0.2.dist-info/WHEEL
tmg_biomechanics-0.0.2.dist-info/top_level.txt
tmg_biomechanics-0.0.2.dist-info/RECORD
