Metadata-Version: 2.1
Name: tmg-biomechanics
Version: 0.0.2
Summary: Time series analysis of tensiomyography (TMG) data
Home-page: https://github.com/ejmastnak/tmg
Author: Elijan Mastnak
Author-email: ejmastnak@gmail.com
License: UNKNOWN
Project-URL: Bug Tracker, https://github.com/ejmastnak/tmg/issues
Platform: UNKNOWN
Classifier: Programming Language :: Python :: 3
Classifier: License :: OSI Approved :: GNU General Public License v3 (GPLv3)
Classifier: Operating System :: OS Independent
Requires-Python: >=3.6
License-File: LICENSE.md
